agency.py
agency_code-1.1.0.dist-info/licenses/LICENSE
agency_code_agent/__init__.py
agency_code_agent/agency_code_agent.py
agency_code_agent/instructions-gpt-5.md
agency_code_agent/instructions.md
planner_agent/__init__.py
planner_agent/instructions-gpt-5.md
planner_agent/instructions.md
planner_agent/planner_agent.py
safety/__init__.py
safety/background_monitor.py
safety/cancellation.py
safety/runaway_detector.py
safety/safe_session.py
safety/session_metrics.py
safety/timeout_monitor.py
shared/agent_utils.py
shared/system_hooks.py
shared/utils.py
subagent_example/instructions.md
subagent_example/subagent_example.py
tools/__init__.py
tools/bash.py
tools/claude_web_search.py
tools/edit.py
tools/exit_plan_mode.py
tools/git.py
tools/glob.py
tools/grep.py
tools/ls.py
tools/multi_edit.py
tools/notebook_edit.py
tools/notebook_read.py
tools/read.py
tools/todo_write.py
tools/web_fetch.py
tools/write.py
agency_code-1.1.0.dist-info/METADATA
agency_code-1.1.0.dist-info/WHEEL
agency_code-1.1.0.dist-info/entry_points.txt
agency_code-1.1.0.dist-info/top_level.txt
agency_code-1.1.0.dist-info/RECORD
