Metadata-Version: 2.4
Name: agency-code
Version: 1.1.0
Summary: An intelligent AI development assistant powered by Claude with built-in safety architecture
Author-email: Joseph Pichardo <joeyjoe808@users.noreply.github.com>
Maintainer-email: Joseph Pichardo <joeyjoe808@users.noreply.github.com>
License: MIT
Project-URL: Homepage, https://github.com/joeyjoe808/Agent-C
Project-URL: Documentation, https://github.com/joeyjoe808/Agent-C/blob/main/ASKME.md
Project-URL: Repository, https://github.com/joeyjoe808/Agent-C.git
Project-URL: Issues, https://github.com/joeyjoe808/Agent-C/issues
Keywords: ai,claude,agent,developer-assistant,cli,anthropic,multi-agent,code-generation,ai-assistant
Classifier: Development Status :: 4 - Beta
Classifier: Intended Audience :: Developers
Classifier: License :: OSI Approved :: MIT License
Classifier: Operating System :: OS Independent
Classifier: Programming Language :: Python :: 3
Classifier: Programming Language :: Python :: 3.13
Classifier: Topic :: Software Development :: Code Generators
Classifier: Topic :: Software Development :: Libraries :: Application Frameworks
Classifier: Environment :: Console
Requires-Python: <3.14,>=3.13
License-File: LICENSE
Requires-Dist: openai-agents[litellm]==0.4.1
Requires-Dist: litellm>=1.0.0
Requires-Dist: beautifulsoup4>=4.9.0
Requires-Dist: python-dotenv>=0.19.0
Requires-Dist: pydantic>=2.0.0
Requires-Dist: requests>=2.25.0
Requires-Dist: dulwich>=0.21.6
Provides-Extra: dev
Requires-Dist: pytest>=6.0.0; extra == "dev"
Requires-Dist: pytest-asyncio>=0.21.0; extra == "dev"
Dynamic: license-file
